{
    "name":"图标库",
    "description":"自用图标库",
    "icons":[
        {
            "name":"5iTV.png",
            "url":"https://hub.nan.ge/QuantumultX/Icon/5iTV.png"
        },
        {
            "name":"HC.png",
            "url":"https://hub.nan.ge/QuantumultX/Icon/HC.png"
        },
        {
            "name":"AbemaTV.png",
            "url":"https://hub.nan.ge/QuantumultX/Icon/AbemaTV.png"
        },
        {
            "name":"AdBlack.png",
            "url":"https://hub.nan.ge/QuantumultX/Icon/AdBlack.png"
        },
        {
            "name":"Advertising.png",
            "url":"https://hub.nan.ge/QuantumultX/Icon/Advertising.png"
        },
        {
            "name":"AdWhite.png",
            "url":"https://hub.nan.ge/QuantumultX/Icon/AdWhite.png"
        },
        {
            "name":"AfreecaTV.png",
            "url":"https://hub.nan.ge/QuantumultX/Icon/AfreecaTV.png"
        },
        {
            "name":"Africa_Map.png",
            "url":"https://hub.nan.ge/QuantumultX/Icon/Africa_Map.png"
        },
        {
            "name":"AGA.png",
            "url":"https://hub.nan.ge/QuantumultX/Icon/AGA.png"
        },
        {
            "name":"AIA.png",
            "url":"https://hub.nan.ge/QuantumultX/Icon/AIA.png"
        },
        {
            "name":"Airport.png",
            "url":"https://hub.nan.ge/QuantumultX/Icon/Airport.png"
        },
        {
            "name":"Alibaba.png",
            "url":"https://hub.nan.ge/QuantumultX/Icon/Alibaba.png"
        },
        {
            "name":"All4.png",
            "url":"https://hub.nan.ge/QuantumultX/Icon/All4.png"
        },
        {
            "name":"Amazon.png",
            "url":"https://hub.nan.ge/QuantumultX/Icon/Amazon.png"
        },
        {
            "name":"Amazon_1.png",
            "url":"https://hub.nan.ge/QuantumultX/Icon/Amazon_1.png"
        },
        {
            "name":"America_Map.png",
            "url":"https://hub.nan.ge/QuantumultX/Icon/America_Map.png"
        },
        {
            "name":"Apple.png",
            "url":"https://hub.nan.ge/QuantumultX/Icon/Apple.png"
        },
        {
            "name":"Apple_1.png",
            "url":"https://hub.nan.ge/QuantumultX/Icon/Apple_1.png"
        },
        {
            "name":"Apple_2.png",
            "url":"https://hub.nan.ge/QuantumultX/Icon/Apple_2.png"
        },
        {
            "name":"Apple_Fitness+.png",
            "url":"https://hub.nan.ge/QuantumultX/Icon/Apple_Fitness+.png"
        },
        {
            "name":"Apple_Fitness+_Letter.png",
            "url":"https://hub.nan.ge/QuantumultX/Icon/Apple_Fitness+_Letter.png"
        },
        {
            "name":"Apple_Fitness.png",
            "url":"https://hub.nan.ge/QuantumultX/Icon/Apple_Fitness.png"
        },
        {
            "name":"Apple_Music.png",
            "url":"https://hub.nan.ge/QuantumultX/Icon/Apple_Music.png"
        },
        {
            "name":"Apple_News.png",
            "url":"https://hub.nan.ge/QuantumultX/Icon/Apple_News.png"
        },
        {
            "name":"Apple_TV.png",
            "url":"https://hub.nan.ge/QuantumultX/Icon/Apple_TV.png"
        },
        {
            "name":"Apple_TV_Plus.png",
            "url":"https://hub.nan.ge/QuantumultX/Icon/Apple_TV_Plus.png"
        },
        {
            "name":"Apple_Update.png",
            "url":"https://hub.nan.ge/QuantumultX/Icon/Apple_Update.png"
        },
        {
            "name":"App_Store.png",
            "url":"https://hub.nan.ge/QuantumultX/Icon/App_Store.png"
        },
        {
            "name":"Area.png",
            "url":"https://hub.nan.ge/QuantumultX/Icon/Area.png"
        },
        {
            "name":"Asia_Map.png",
            "url":"https://hub.nan.ge/QuantumultX/Icon/Asia_Map.png"
        },
        {
            "name":"AU.png",
            "url":"https://hub.nan.ge/QuantumultX/Icon/AU.png"
        },
        {
            "name":"Australia.png",
            "url":"https://hub.nan.ge/QuantumultX/Icon/Australia.png"
        },
        {
            "name":"Auto.png",
            "url":"https://hub.nan.ge/QuantumultX/Icon/Auto.png"
        },
        {
            "name":"Available.png",
            "url":"https://hub.nan.ge/QuantumultX/Icon/Available.png"
        },
        {
            "name":"Available_1.png",
            "url":"https://hub.nan.ge/QuantumultX/Icon/Available_1.png"
        },
        {
            "name":"Azure.png",
            "url":"https://hub.nan.ge/QuantumultX/Icon/Azure.png"
        },
        {
            "name":"Back.png",
            "url":"https://hub.nan.ge/QuantumultX/Icon/Back.png"
        },
        {
            "name":"Bahamut.png",
            "url":"https://hub.nan.ge/QuantumultX/Icon/Bahamut.png"
        },
        {
            "name":"Bamboo.png",
            "url":"https://hub.nan.ge/QuantumultX/Icon/Bamboo.png"
        },
        {
            "name":"BBC_iPlayer.png",
            "url":"https://hub.nan.ge/QuantumultX/Icon/BBC_iPlayer.png"
        },
        {
            "name":"BBC_iPlayer_1.png",
            "url":"https://hub.nan.ge/QuantumultX/Icon/BBC_iPlayer_1.png"
        },
        {
            "name":"BBC_iPlayer_2.png",
            "url":"https://hub.nan.ge/QuantumultX/Icon/BBC_iPlayer_2.png"
        },
        {
            "name":"BGP.png",
            "url":"https://hub.nan.ge/QuantumultX/Icon/BGP.png"
        },
        {
            "name":"bilibili.png",
            "url":"https://hub.nan.ge/QuantumultX/Icon/bilibili.png"
        },
        {
            "name":"bilibili_1.png",
            "url":"https://hub.nan.ge/QuantumultX/Icon/bilibili_1.png"
        },
        {
            "name":"bilibili_2.png",
            "url":"https://hub.nan.ge/QuantumultX/Icon/bilibili_2.png"
        },
        {
            "name":"bilibili_3.png",
            "url":"https://hub.nan.ge/QuantumultX/Icon/bilibili_3.png"
        },
        {
            "name":"bilibili_4.png",
            "url":"https://hub.nan.ge/QuantumultX/Icon/bilibili_4.png"
        },
        {
            "name":"Blackhole.png",
            "url":"https://hub.nan.ge/QuantumultX/Icon/Blackhole.png"
        },
        {
            "name":"Blinkload.png",
            "url":"https://hub.nan.ge/QuantumultX/Icon/Blinkload.png"
        },
        {
            "name":"Blinkload_1.png",
            "url":"https://hub.nan.ge/QuantumultX/Icon/Blinkload_1.png"
        },
        {
            "name":"Bookpedia.png",
            "url":"https://hub.nan.ge/QuantumultX/Icon/Bookpedia.png"
        },
        {
            "name":"BosLife.png",
            "url":"https://hub.nan.ge/QuantumultX/Icon/BosLife.png"
        },
        {
            "name":"BosLife_1.png",
            "url":"https://hub.nan.ge/QuantumultX/Icon/BosLife_1.png"
        },
        {
            "name":"Bot.png",
            "url":"https://hub.nan.ge/QuantumultX/Icon/Bot.png"
        },
        {
            "name":"BR.png",
            "url":"https://hub.nan.ge/QuantumultX/Icon/BR.png"
        },
        {
            "name":"Brazil.png",
            "url":"https://hub.nan.ge/QuantumultX/Icon/Brazil.png"
        },
        {
            "name":"Bypass.png",
            "url":"https://hub.nan.ge/QuantumultX/Icon/Bypass.png"
        },
        {
            "name":"CA.png",
            "url":"https://hub.nan.ge/QuantumultX/Icon/CA.png"
        },
        {
            "name":"Canada.png",
            "url":"https://hub.nan.ge/QuantumultX/Icon/Canada.png"
        },
        {
            "name":"Cat.png",
            "url":"https://hub.nan.ge/QuantumultX/Icon/Cat.png"
        },
        {
            "name":"Catnet.png",
            "url":"https://hub.nan.ge/QuantumultX/Icon/Catnet.png"
        },
        {
            "name":"CC.png",
            "url":"https://hub.nan.ge/QuantumultX/Icon/CC.png"
        },
        {
            "name":"Cellular.png",
            "url":"https://hub.nan.ge/QuantumultX/Icon/Cellular.png"
        },
        {
            "name":"China.png",
            "url":"https://hub.nan.ge/QuantumultX/Icon/China.png"
        },
        {
            "name":"China_Map.png",
            "url":"https://hub.nan.ge/QuantumultX/Icon/China_Map.png"
        },
        {
            "name":"Cloudflare.png",
            "url":"https://hub.nan.ge/QuantumultX/Icon/Cloudflare.png"
        },
        {
            "name":"Clubhouse.png",
            "url":"https://hub.nan.ge/QuantumultX/Icon/Clubhouse.png"
        },
        {
            "name":"Clubhouse_1.png",
            "url":"https://hub.nan.ge/QuantumultX/Icon/Clubhouse_1.png"
        },
        {
            "name":"Clubhouse_2.png",
            "url":"https://hub.nan.ge/QuantumultX/Icon/Clubhouse_2.png"
        },
        {
            "name":"CN.png",
            "url":"https://hub.nan.ge/QuantumultX/Icon/CN.png"
        },
        {
            "name":"Cryptocurrency.png",
            "url":"https://hub.nan.ge/QuantumultX/Icon/Cryptocurrency.png"
        },
        {
            "name":"Cryptocurrency_1.png",
            "url":"https://hub.nan.ge/QuantumultX/Icon/Cryptocurrency_1.png"
        },
        {
            "name":"Cryptocurrency_2.png",
            "url":"https://hub.nan.ge/QuantumultX/Icon/Cryptocurrency_2.png"
        },
        {
            "name":"Cryptocurrency_3.png",
            "url":"https://hub.nan.ge/QuantumultX/Icon/Cryptocurrency_3.png"
        },
        {
            "name":"Cydia.png",
            "url":"https://hub.nan.ge/QuantumultX/Icon/Cydia.png"
        },
        {
            "name":"Daily.png",
            "url":"https://hub.nan.ge/QuantumultX/Icon/Daily.png"
        },
        {
            "name":"DAZN.png",
            "url":"https://hub.nan.ge/QuantumultX/Icon/DAZN.png"
        },
        {
            "name":"DAZN_1.png",
            "url":"https://hub.nan.ge/QuantumultX/Icon/DAZN_1.png"
        },
        {
            "name":"DAZN_2.png",
            "url":"https://hub.nan.ge/QuantumultX/Icon/DAZN_2.png"
        },
        {
            "name":"DE.png",
            "url":"https://hub.nan.ge/QuantumultX/Icon/DE.png"
        },
        {
            "name":"deezer.png",
            "url":"https://hub.nan.ge/QuantumultX/Icon/deezer.png"
        },
        {
            "name":"deezer_1.png",
            "url":"https://hub.nan.ge/QuantumultX/Icon/deezer_1.png"
        },
        {
            "name":"deezer_2.png",
            "url":"https://hub.nan.ge/QuantumultX/Icon/deezer_2.png"
        },
        {
            "name":"Dinosaur.png",
            "url":"https://hub.nan.ge/QuantumultX/Icon/Dinosaur.png"
        },
        {
            "name":"Direct.png",
            "url":"https://hub.nan.ge/QuantumultX/Icon/Direct.png"
        },
        {
            "name":"Discord.png",
            "url":"https://hub.nan.ge/QuantumultX/Icon/Discord.png"
        },
        {
            "name":"discovery+.png",
            "url":"https://hub.nan.ge/QuantumultX/Icon/discovery+.png"
        },
        {
            "name":"Disney+.png",
            "url":"https://hub.nan.ge/QuantumultX/Icon/Disney+.png"
        },
        {
            "name":"Disney+_1.png",
            "url":"https://hub.nan.ge/QuantumultX/Icon/Disney+_1.png"
        },
        {
            "name":"Disney+_2.png",
            "url":"https://hub.nan.ge/QuantumultX/Icon/Disney+_2.png"
        },
        {
            "name":"Disney.png",
            "url":"https://hub.nan.ge/QuantumultX/Icon/Disney.png"
        },
        {
            "name":"Domestic.png",
            "url":"https://hub.nan.ge/QuantumultX/Icon/Domestic.png"
        },
        {
            "name":"DomesticMedia.png",
            "url":"https://hub.nan.ge/QuantumultX/Icon/DomesticMedia.png"
        },
        {
            "name":"Download.png",
            "url":"https://hub.nan.ge/QuantumultX/Icon/Download.png"
        },
        {
            "name":"Drill.png",
            "url":"https://hub.nan.ge/QuantumultX/Icon/Drill.png"
        },
        {
            "name":"EG.png",
            "url":"https://hub.nan.ge/QuantumultX/Icon/EG.png"
        },
        {
            "name":"Egypt.png",
            "url":"https://hub.nan.ge/QuantumultX/Icon/Egypt.png"
        },
        {
            "name":"Emby.png",
            "url":"https://hub.nan.ge/QuantumultX/Icon/Emby.png"
        },
        {
            "name":"encoreTVB.png",
            "url":"https://hub.nan.ge/QuantumultX/Icon/encoreTVB.png"
        },
        {
            "name":"ESPN+.png",
            "url":"https://hub.nan.ge/QuantumultX/Icon/ESPN+.png"
        },
        {
            "name":"ESPN+_1.png",
            "url":"https://hub.nan.ge/QuantumultX/Icon/ESPN+_1.png"
        },
        {
            "name":"ESPN+_2.png",
            "url":"https://hub.nan.ge/QuantumultX/Icon/ESPN+_2.png"
        },
        {
            "name":"EU.png",
            "url":"https://hub.nan.ge/QuantumultX/Icon/EU.png"
        },
        {
            "name":"European_Union.png",
            "url":"https://hub.nan.ge/QuantumultX/Icon/European_Union.png"
        },
        {
            "name":"Europe_Map.png",
            "url":"https://hub.nan.ge/QuantumultX/Icon/Europe_Map.png"
        },
        {
            "name":"Facebook.png",
            "url":"https://hub.nan.ge/QuantumultX/Icon/Facebook.png"
        },
        {
            "name":"FI.png",
            "url":"https://hub.nan.ge/QuantumultX/Icon/FI.png"
        },
        {
            "name":"Filter.png",
            "url":"https://hub.nan.ge/QuantumultX/Icon/Filter.png"
        },
        {
            "name":"Final.png",
            "url":"https://hub.nan.ge/QuantumultX/Icon/Final.png"
        },
        {
            "name":"Final_1.png",
            "url":"https://hub.nan.ge/QuantumultX/Icon/Final_1.png"
        },
        {
            "name":"Find_My.png",
            "url":"https://hub.nan.ge/QuantumultX/Icon/Find_My.png"
        },
        {
            "name":"Finland.png",
            "url":"https://hub.nan.ge/QuantumultX/Icon/Finland.png"
        },
        {
            "name":"Flamingo.png",
            "url":"https://hub.nan.ge/QuantumultX/Icon/Flamingo.png"
        },
        {
            "name":"ForeignMedia.png",
            "url":"https://hub.nan.ge/QuantumultX/Icon/ForeignMedia.png"
        },
        {
            "name":"FOX.png",
            "url":"https://hub.nan.ge/QuantumultX/Icon/FOX.png"
        },
        {
            "name":"FR.png",
            "url":"https://hub.nan.ge/QuantumultX/Icon/FR.png"
        },
        {
            "name":"France.png",
            "url":"https://hub.nan.ge/QuantumultX/Icon/France.png"
        },
        {
            "name":"friDay.png",
            "url":"https://hub.nan.ge/QuantumultX/Icon/friDay.png"
        },
        {
            "name":"fuboTV.png",
            "url":"https://hub.nan.ge/QuantumultX/Icon/fuboTV.png"
        },
        {
            "name":"Game.png",
            "url":"https://hub.nan.ge/QuantumultX/Icon/Game.png"
        },
        {
            "name":"Germany.png",
            "url":"https://hub.nan.ge/QuantumultX/Icon/Germany.png"
        },
        {
            "name":"GIA.png",
            "url":"https://hub.nan.ge/QuantumultX/Icon/GIA.png"
        },
        {
            "name":"GitHub.png",
            "url":"https://hub.nan.ge/QuantumultX/Icon/GitHub.png"
        },
        {
            "name":"GitHub_Letter.png",
            "url":"https://hub.nan.ge/QuantumultX/Icon/GitHub_Letter.png"
        },
        {
            "name":"Global.png",
            "url":"https://hub.nan.ge/QuantumultX/Icon/Global.png"
        },
        {
            "name":"Google.png",
            "url":"https://hub.nan.ge/QuantumultX/Icon/Google.png"
        },
        {
            "name":"Google_Drive.png",
            "url":"https://hub.nan.ge/QuantumultX/Icon/Google_Drive.png"
        },
        {
            "name":"Google_Opinion_Rewards.png",
            "url":"https://hub.nan.ge/QuantumultX/Icon/Google_Opinion_Rewards.png"
        },
        {
            "name":"Google_Search.png",
            "url":"https://hub.nan.ge/QuantumultX/Icon/Google_Search.png"
        },
        {
            "name":"HBO.png",
            "url":"https://hub.nan.ge/QuantumultX/Icon/HBO.png"
        },
        {
            "name":"HBO_1.png",
            "url":"https://hub.nan.ge/QuantumultX/Icon/HBO_1.png"
        },
        {
            "name":"HBO_2.png",
            "url":"https://hub.nan.ge/QuantumultX/Icon/HBO_2.png"
        },
        {
            "name":"HBO_GO.png",
            "url":"https://hub.nan.ge/QuantumultX/Icon/HBO_GO.png"
        },
        {
            "name":"HBO_GO_1.png",
            "url":"https://hub.nan.ge/QuantumultX/Icon/HBO_GO_1.png"
        },
        {
            "name":"HBO_GO_2.png",
            "url":"https://hub.nan.ge/QuantumultX/Icon/HBO_GO_2.png"
        },
        {
            "name":"HBO_Max.png",
            "url":"https://hub.nan.ge/QuantumultX/Icon/HBO_Max.png"
        },
        {
            "name":"Heart.png",
            "url":"https://hub.nan.ge/QuantumultX/Icon/Heart.png"
        },
        {
            "name":"Hijacking.png",
            "url":"https://hub.nan.ge/QuantumultX/Icon/Hijacking.png"
        },
        {
            "name":"HK.png",
            "url":"https://hub.nan.ge/QuantumultX/Icon/HK.png"
        },
        {
            "name":"HKMTMedia.png",
            "url":"https://hub.nan.ge/QuantumultX/Icon/HKMTMedia.png"
        },
        {
            "name":"Hong_Kong.png",
            "url":"https://hub.nan.ge/QuantumultX/Icon/Hong_Kong.png"
        },
        {
            "name":"Hulu.png",
            "url":"https://hub.nan.ge/QuantumultX/Icon/Hulu.png"
        },
        {
            "name":"Hulu_1.png",
            "url":"https://hub.nan.ge/QuantumultX/Icon/Hulu_1.png"
        },
        {
            "name":"iCloud.png",
            "url":"https://hub.nan.ge/QuantumultX/Icon/iCloud.png"
        },
        {
            "name":"IEPL.png",
            "url":"https://hub.nan.ge/QuantumultX/Icon/IEPL.png"
        },
        {
            "name":"IN.png",
            "url":"https://hub.nan.ge/QuantumultX/Icon/IN.png"
        },
        {
            "name":"India.png",
            "url":"https://hub.nan.ge/QuantumultX/Icon/India.png"
        },
        {
            "name":"Infuse.png",
            "url":"https://hub.nan.ge/QuantumultX/Icon/Infuse.png"
        },
        {
            "name":"Infuse_7.png",
            "url":"https://hub.nan.ge/QuantumultX/Icon/Infuse_7.png"
        },
        {
            "name":"Ingress.png",
            "url":"https://hub.nan.ge/QuantumultX/Icon/Ingress.png"
        },
        {
            "name":"Instagram.png",
            "url":"https://hub.nan.ge/QuantumultX/Icon/Instagram.png"
        },
        {
            "name":"IPLC.png",
            "url":"https://hub.nan.ge/QuantumultX/Icon/IPLC.png"
        },
        {
            "name":"iQIYI&bilibili.png",
            "url":"https://hub.nan.ge/QuantumultX/Icon/iQIYI&bilibili.png"
        },
        {
            "name":"iQIYI.png",
            "url":"https://hub.nan.ge/QuantumultX/Icon/iQIYI.png"
        },
        {
            "name":"ITV.png",
            "url":"https://hub.nan.ge/QuantumultX/Icon/ITV.png"
        },
        {
            "name":"ITV_1.png",
            "url":"https://hub.nan.ge/QuantumultX/Icon/ITV_1.png"
        },
        {
            "name":"ITV_2.png",
            "url":"https://hub.nan.ge/QuantumultX/Icon/ITV_2.png"
        },
        {
            "name":"Japan.png",
            "url":"https://hub.nan.ge/QuantumultX/Icon/Japan.png"
        },
        {
            "name":"JOOX.png",
            "url":"https://hub.nan.ge/QuantumultX/Icon/JOOX.png"
        },
        {
            "name":"JP.png",
            "url":"https://hub.nan.ge/QuantumultX/Icon/JP.png"
        },
        {
            "name":"KKBOX.png",
            "url":"https://hub.nan.ge/QuantumultX/Icon/KKBOX.png"
        },
        {
            "name":"KKTV.png",
            "url":"https://hub.nan.ge/QuantumultX/Icon/KKTV.png"
        },
        {
            "name":"Korea.png",
            "url":"https://hub.nan.ge/QuantumultX/Icon/Korea.png"
        },
        {
            "name":"KR.png",
            "url":"https://hub.nan.ge/QuantumultX/Icon/KR.png"
        },
        {
            "name":"Lab.png",
            "url":"https://hub.nan.ge/QuantumultX/Icon/Lab.png"
        },
        {
            "name":"Lambda.png",
            "url":"https://hub.nan.ge/QuantumultX/Icon/Lambda.png"
        },
        {
            "name":"League_of_Legends.png",
            "url":"https://hub.nan.ge/QuantumultX/Icon/League_of_Legends.png"
        },
        {
            "name":"Line.png",
            "url":"https://hub.nan.ge/QuantumultX/Icon/Line.png"
        },
        {
            "name":"LineTV.png",
            "url":"https://hub.nan.ge/QuantumultX/Icon/LineTV.png"
        },
        {
            "name":"LiTV.png",
            "url":"https://hub.nan.ge/QuantumultX/Icon/LiTV.png"
        },
        {
            "name":"Lock.png",
            "url":"https://hub.nan.ge/QuantumultX/Icon/Lock.png"
        },
        {
            "name":"LOL.png",
            "url":"https://hub.nan.ge/QuantumultX/Icon/LOL.png"
        },
        {
            "name":"Loop.png",
            "url":"https://hub.nan.ge/QuantumultX/Icon/Loop.png"
        },
        {
            "name":"Luffy.png",
            "url":"https://hub.nan.ge/QuantumultX/Icon/Luffy.png"
        },
        {
            "name":"Macao.png",
            "url":"https://hub.nan.ge/QuantumultX/Icon/Macao.png"
        },
        {
            "name":"Magic.png",
            "url":"https://hub.nan.ge/QuantumultX/Icon/Magic.png"
        },
        {
            "name":"Mail.png",
            "url":"https://hub.nan.ge/QuantumultX/Icon/Mail.png"
        },
        {
            "name":"Malaysia.png",
            "url":"https://hub.nan.ge/QuantumultX/Icon/Malaysia.png"
        },
        {
            "name":"Media.png",
            "url":"https://hub.nan.ge/QuantumultX/Icon/Media.png"
        },
        {
            "name":"Mickey.png",
            "url":"https://hub.nan.ge/QuantumultX/Icon/Mickey.png"
        },
        {
            "name":"Microsoft.png",
            "url":"https://hub.nan.ge/QuantumultX/Icon/Microsoft.png"
        },
        {
            "name":"MO.png",
            "url":"https://hub.nan.ge/QuantumultX/Icon/MO.png"
        },
        {
            "name":"Mouse.png",
            "url":"https://hub.nan.ge/QuantumultX/Icon/Mouse.png"
        },
        {
            "name":"Music_Enhance.png",
            "url":"https://hub.nan.ge/QuantumultX/Icon/Music_Enhance.png"
        },
        {
            "name":"MY.png",
            "url":"https://hub.nan.ge/QuantumultX/Icon/MY.png"
        },
        {
            "name":"My5.png",
            "url":"https://hub.nan.ge/QuantumultX/Icon/My5.png"
        },
        {
            "name":"myTV_SUPER.png",
            "url":"https://hub.nan.ge/QuantumultX/Icon/myTV_SUPER.png"
        },
        {
            "name":"NBA.png",
            "url":"https://hub.nan.ge/QuantumultX/Icon/NBA.png"
        },
        {
            "name":"NBC.png",
            "url":"https://hub.nan.ge/QuantumultX/Icon/NBC.png"
        },
        {
            "name":"Netease_Music.png",
            "url":"https://hub.nan.ge/QuantumultX/Icon/Netease_Music.png"
        },
        {
            "name":"Netease_Music_Unlock.png",
            "url":"https://hub.nan.ge/QuantumultX/Icon/Netease_Music_Unlock.png"
        },
        {
            "name":"Netflix.png",
            "url":"https://hub.nan.ge/QuantumultX/Icon/Netflix.png"
        },
        {
            "name":"Netflix_Letter.png",
            "url":"https://hub.nan.ge/QuantumultX/Icon/Netflix_Letter.png"
        },
        {
            "name":"Nfcloud.png",
            "url":"https://hub.nan.ge/QuantumultX/Icon/Nfcloud.png"
        },
        {
            "name":"niconico.png",
            "url":"https://hub.nan.ge/QuantumultX/Icon/niconico.png"
        },
        {
            "name":"niconico_1.png",
            "url":"https://hub.nan.ge/QuantumultX/Icon/niconico_1.png"
        },
        {
            "name":"niconico_2.png",
            "url":"https://hub.nan.ge/QuantumultX/Icon/niconico_2.png"
        },
        {
            "name":"Notion.png",
            "url":"https://hub.nan.ge/QuantumultX/Icon/Notion.png"
        },
        {
            "name":"nowe.png",
            "url":"https://hub.nan.ge/QuantumultX/Icon/nowe.png"
        },
        {
            "name":"Null_Nation.png",
            "url":"https://hub.nan.ge/QuantumultX/Icon/Null_Nation.png"
        },
        {
            "name":"Oceania_Map.png",
            "url":"https://hub.nan.ge/QuantumultX/Icon/Oceania_Map.png"
        },
        {
            "name":"OneDrive.png",
            "url":"https://hub.nan.ge/QuantumultX/Icon/OneDrive.png"
        },
        {
            "name":"Ox.png",
            "url":"https://hub.nan.ge/QuantumultX/Icon/Ox.png"
        },
        {
            "name":"Panda.png",
            "url":"https://hub.nan.ge/QuantumultX/Icon/Panda.png"
        },
        {
            "name":"Pandora.png",
            "url":"https://hub.nan.ge/QuantumultX/Icon/Pandora.png"
        },
        {
            "name":"Paramount.png",
            "url":"https://hub.nan.ge/QuantumultX/Icon/Paramount.png"
        },
        {
            "name":"PayPal.png",
            "url":"https://hub.nan.ge/QuantumultX/Icon/PayPal.png"
        },
        {
            "name":"PBS.png",
            "url":"https://hub.nan.ge/QuantumultX/Icon/PBS.png"
        },
        {
            "name":"Peacock.png",
            "url":"https://hub.nan.ge/QuantumultX/Icon/Peacock.png"
        },
        {
            "name":"Peacock_1.png",
            "url":"https://hub.nan.ge/QuantumultX/Icon/Peacock_1.png"
        },
        {
            "name":"Peacock_2.png",
            "url":"https://hub.nan.ge/QuantumultX/Icon/Peacock_2.png"
        },
        {
            "name":"PH.png",
            "url":"https://hub.nan.ge/QuantumultX/Icon/PH.png"
        },
        {
            "name":"Philippines.png",
            "url":"https://hub.nan.ge/QuantumultX/Icon/Philippines.png"
        },
        {
            "name":"Pig.png",
            "url":"https://hub.nan.ge/QuantumultX/Icon/Pig.png"
        },
        {
            "name":"Pornhub.png",
            "url":"https://hub.nan.ge/QuantumultX/Icon/Pornhub.png"
        },
        {
            "name":"Pornhub_1.png",
            "url":"https://hub.nan.ge/QuantumultX/Icon/Pornhub_1.png"
        },
        {
            "name":"Pornhub_2.png",
            "url":"https://hub.nan.ge/QuantumultX/Icon/Pornhub_2.png"
        },
        {
            "name":"PostBox.png",
            "url":"https://hub.nan.ge/QuantumultX/Icon/PostBox.png"
        },
        {
            "name":"PostBox_1.png",
            "url":"https://hub.nan.ge/QuantumultX/Icon/PostBox_1.png"
        },
        {
            "name":"Prime_Video.png",
            "url":"https://hub.nan.ge/QuantumultX/Icon/Prime_Video.png"
        },
        {
            "name":"Prime_Video_1.png",
            "url":"https://hub.nan.ge/QuantumultX/Icon/Prime_Video_1.png"
        },
        {
            "name":"Prime_Video_2.png",
            "url":"https://hub.nan.ge/QuantumultX/Icon/Prime_Video_2.png"
        },
        {
            "name":"Proxy.png",
            "url":"https://hub.nan.ge/QuantumultX/Icon/Proxy.png"
        },
        {
            "name":"Puzzle.png",
            "url":"https://hub.nan.ge/QuantumultX/Icon/Puzzle.png"
        },
        {
            "name":"QQ.png",
            "url":"https://hub.nan.ge/QuantumultX/Icon/QQ.png"
        },
        {
            "name":"Quantumult_X.png",
            "url":"https://hub.nan.ge/QuantumultX/Icon/Quantumult_X.png"
        },
        {
            "name":"Qure.png",
            "url":"https://hub.nan.ge/QuantumultX/Icon/Qure.png"
        },
        {
            "name":"Reject.png",
            "url":"https://hub.nan.ge/QuantumultX/Icon/Reject.png"
        },
        {
            "name":"Rocket.png",
            "url":"https://hub.nan.ge/QuantumultX/Icon/Rocket.png"
        },
        {
            "name":"Round_Robin.png",
            "url":"https://hub.nan.ge/QuantumultX/Icon/Round_Robin.png"
        },
        {
            "name":"Round_Robin_1.png",
            "url":"https://hub.nan.ge/QuantumultX/Icon/Round_Robin_1.png"
        },
        {
            "name":"RU.png",
            "url":"https://hub.nan.ge/QuantumultX/Icon/RU.png"
        },
        {
            "name":"Russia.png",
            "url":"https://hub.nan.ge/QuantumultX/Icon/Russia.png"
        },
        {
            "name":"Scholar.png",
            "url":"https://hub.nan.ge/QuantumultX/Icon/Scholar.png"
        },
        {
            "name":"Server.png",
            "url":"https://hub.nan.ge/QuantumultX/Icon/Server.png"
        },
        {
            "name":"SG.png",
            "url":"https://hub.nan.ge/QuantumultX/Icon/SG.png"
        },
        {
            "name":"Singapore.png",
            "url":"https://hub.nan.ge/QuantumultX/Icon/Singapore.png"
        },
        {
            "name":"Siri.png",
            "url":"https://hub.nan.ge/QuantumultX/Icon/Siri.png"
        },
        {
            "name":"Sling_TV.png",
            "url":"https://hub.nan.ge/QuantumultX/Icon/Sling_TV.png"
        },
        {
            "name":"Spark.png",
            "url":"https://hub.nan.ge/QuantumultX/Icon/Spark.png"
        },
        {
            "name":"Speedtest.png",
            "url":"https://hub.nan.ge/QuantumultX/Icon/Speedtest.png"
        },
        {
            "name":"Spotify.png",
            "url":"https://hub.nan.ge/QuantumultX/Icon/Spotify.png"
        },
        {
            "name":"SSID.png",
            "url":"https://hub.nan.ge/QuantumultX/Icon/SSID.png"
        },
        {
            "name":"SSID_1.png",
            "url":"https://hub.nan.ge/QuantumultX/Icon/SSID_1.png"
        },
        {
            "name":"SSL.png",
            "url":"https://hub.nan.ge/QuantumultX/Icon/SSL.png"
        },
        {
            "name":"Stack.png",
            "url":"https://hub.nan.ge/QuantumultX/Icon/Stack.png"
        },
        {
            "name":"Star.png",
            "url":"https://hub.nan.ge/QuantumultX/Icon/Star.png"
        },
        {
            "name":"Star_1.png",
            "url":"https://hub.nan.ge/QuantumultX/Icon/Star_1.png"
        },
        {
            "name":"Star+.png",
            "url":"https://hub.nan.ge/QuantumultX/Icon/Star+.png"
        },
        {
            "name":"Static.png",
            "url":"https://hub.nan.ge/QuantumultX/Icon/Static.png"
        },
        {
            "name":"Static_1.png",
            "url":"https://hub.nan.ge/QuantumultX/Icon/Static_1.png"
        },
        {
            "name":"Steam.png",
            "url":"https://hub.nan.ge/QuantumultX/Icon/Steam.png"
        },
        {
            "name":"Streaming.png",
            "url":"https://hub.nan.ge/QuantumultX/Icon/Streaming.png"
        },
        {
            "name":"StreamingCN.png",
            "url":"https://hub.nan.ge/QuantumultX/Icon/StreamingCN.png"
        },
        {
            "name":"StreamingSE.png",
            "url":"https://hub.nan.ge/QuantumultX/Icon/StreamingSE.png"
        },
        {
            "name":"TAG.png",
            "url":"https://hub.nan.ge/QuantumultX/Icon/TAG.png"
        },
        {
            "name":"Taiwan.png",
            "url":"https://hub.nan.ge/QuantumultX/Icon/Taiwan.png"
        },
        {
            "name":"Taobao.png",
            "url":"https://hub.nan.ge/QuantumultX/Icon/Taobao.png"
        },
        {
            "name":"Telegram.png",
            "url":"https://hub.nan.ge/QuantumultX/Icon/Telegram.png"
        },
        {
            "name":"Telegram_X.png",
            "url":"https://hub.nan.ge/QuantumultX/Icon/Telegram_X.png"
        },
        {
            "name":"TestFlight.png",
            "url":"https://hub.nan.ge/QuantumultX/Icon/TestFlight.png"
        },
        {
            "name":"TestFlight_1.png",
            "url":"https://hub.nan.ge/QuantumultX/Icon/TestFlight_1.png"
        },
        {
            "name":"TestFlight_2.png",
            "url":"https://hub.nan.ge/QuantumultX/Icon/TestFlight_2.png"
        },
        {
            "name":"TH.png",
            "url":"https://hub.nan.ge/QuantumultX/Icon/TH.png"
        },
        {
            "name":"Thailand.png",
            "url":"https://hub.nan.ge/QuantumultX/Icon/Thailand.png"
        },
        {
            "name":"TIDAL.png",
            "url":"https://hub.nan.ge/QuantumultX/Icon/TIDAL.png"
        },
        {
            "name":"TIDAL_1.png",
            "url":"https://hub.nan.ge/QuantumultX/Icon/TIDAL_1.png"
        },
        {
            "name":"TIDAL_2.png",
            "url":"https://hub.nan.ge/QuantumultX/Icon/TIDAL_2.png"
        },
        {
            "name":"TikTok.png",
            "url":"https://hub.nan.ge/QuantumultX/Icon/TikTok.png"
        },
        {
            "name":"TikTok_1.png",
            "url":"https://hub.nan.ge/QuantumultX/Icon/TikTok_1.png"
        },
        {
            "name":"TikTok_2.png",
            "url":"https://hub.nan.ge/QuantumultX/Icon/TikTok_2.png"
        },
        {
            "name":"TR.png",
            "url":"https://hub.nan.ge/QuantumultX/Icon/TR.png"
        },
        {
            "name":"Tubi.png",
            "url":"https://hub.nan.ge/QuantumultX/Icon/Tubi.png"
        },
        {
            "name":"Turkey.png",
            "url":"https://hub.nan.ge/QuantumultX/Icon/Turkey.png"
        },
        {
            "name":"TVB.png",
            "url":"https://hub.nan.ge/QuantumultX/Icon/TVB.png"
        },
        {
            "name":"TW.png",
            "url":"https://hub.nan.ge/QuantumultX/Icon/TW.png"
        },
        {
            "name":"Twitch.png",
            "url":"https://hub.nan.ge/QuantumultX/Icon/Twitch.png"
        },
        {
            "name":"Twitter.png",
            "url":"https://hub.nan.ge/QuantumultX/Icon/Twitter.png"
        },
        {
            "name":"UK.png",
            "url":"https://hub.nan.ge/QuantumultX/Icon/UK.png"
        },
        {
            "name":"ULB.png",
            "url":"https://hub.nan.ge/QuantumultX/Icon/ULB.png"
        },
        {
            "name":"ULB_1.png",
            "url":"https://hub.nan.ge/QuantumultX/Icon/ULB_1.png"
        },
        {
            "name":"UN.png",
            "url":"https://hub.nan.ge/QuantumultX/Icon/UN.png"
        },
        {
            "name":"United_Kingdom.png",
            "url":"https://hub.nan.ge/QuantumultX/Icon/United_Kingdom.png"
        },
        {
            "name":"United_Nations.png",
            "url":"https://hub.nan.ge/QuantumultX/Icon/United_Nations.png"
        },
        {
            "name":"United_States.png",
            "url":"https://hub.nan.ge/QuantumultX/Icon/United_States.png"
        },
        {
            "name":"United_States_Map.png",
            "url":"https://hub.nan.ge/QuantumultX/Icon/United_States_Map.png"
        },
        {
            "name":"Unlock.png",
            "url":"https://hub.nan.ge/QuantumultX/Icon/Unlock.png"
        },
        {
            "name":"US.png",
            "url":"https://hub.nan.ge/QuantumultX/Icon/US.png"
        },
        {
            "name":"Vimeo.png",
            "url":"https://hub.nan.ge/QuantumultX/Icon/Vimeo.png"
        },
        {
            "name":"VIP.png",
            "url":"https://hub.nan.ge/QuantumultX/Icon/VIP.png"
        },
        {
            "name":"Viu.png",
            "url":"https://hub.nan.ge/QuantumultX/Icon/Viu.png"
        },
        {
            "name":"ViuTV.png",
            "url":"https://hub.nan.ge/QuantumultX/Icon/ViuTV.png"
        },
        {
            "name":"Want_Want.png",
            "url":"https://hub.nan.ge/QuantumultX/Icon/Want_Want.png"
        },
        {
            "name":"Want_Want_1.png",
            "url":"https://hub.nan.ge/QuantumultX/Icon/Want_Want_1.png"
        },
        {
            "name":"WeChat.png",
            "url":"https://hub.nan.ge/QuantumultX/Icon/WeChat.png"
        },
        {
            "name":"WeTV.png",
            "url":"https://hub.nan.ge/QuantumultX/Icon/WeTV.png"
        },
        {
            "name":"WeTV_Letter.png",
            "url":"https://hub.nan.ge/QuantumultX/Icon/WeTV_Letter.png"
        },
        {
            "name":"WiFi.png",
            "url":"https://hub.nan.ge/QuantumultX/Icon/WiFi.png"
        },
        {
            "name":"Windows.png",
            "url":"https://hub.nan.ge/QuantumultX/Icon/Windows.png"
        },
        {
            "name":"Windows_11.png",
            "url":"https://hub.nan.ge/QuantumultX/Icon/Windows_11.png"
        },
        {
            "name":"World_Map.png",
            "url":"https://hub.nan.ge/QuantumultX/Icon/World_Map.png"
        },
        {
            "name":"Yahoo.png",
            "url":"https://hub.nan.ge/QuantumultX/Icon/Yahoo.png"
        },
        {
            "name":"Yahoo_1.png",
            "url":"https://hub.nan.ge/QuantumultX/Icon/Yahoo_1.png"
        },
        {
            "name":"YouTube.png",
            "url":"https://hub.nan.ge/QuantumultX/Icon/YouTube.png"
        },
        {
            "name":"YouTube_Letter.png",
            "url":"https://hub.nan.ge/QuantumultX/Icon/YouTube_Letter.png"
        },
        {
            "name":"YouTube_Music.png",
            "url":"https://hub.nan.ge/QuantumultX/Icon/YouTube_Music.png"
        }
    ]
}